pywkmisc/__init__.py
pywkmisc/config.py
pywkmisc/date_utils.py
pywkmisc/file_utils.py
pywkmisc/http_client_utils.py
pywkmisc/image_utils.py
pywkmisc/mimetype_utils.py
pywkmisc/multipartform_data.py
pywkmisc/string_utils.py
Pywkmisc-1.0.5.2.dist-info/METADATA
Pywkmisc-1.0.5.2.dist-info/WHEEL
Pywkmisc-1.0.5.2.dist-info/top_level.txt
Pywkmisc-1.0.5.2.dist-info/RECORD
