Metadata-Version: 2.1
Name: Pywkmisc
Version: 1.0.5.2
Summary: wangkai python misc tools
Home-page: http://blog.wangkaicn.cn
Author: wangkai
Author-email: 1719456@qq.com
License: MIT License
Keywords: wangkai python misc tools
Platform: any
Requires-Dist: jsonpath
Requires-Dist: requests
